ros_rosidl_cmake-4.6.6.data/data/lib/python3.12/site-packages/rosidl_cmake/__init__.py
ros_rosidl_cmake-4.6.6.data/data/lib/python3.12/site-packages/rosidl_cmake/__pycache__/__init__.cpython-312.pyc
ros_rosidl_cmake-4.6.6.data/data/lib/python3.12/site-packages/rosidl_cmake-4.6.6-py3.12.egg-info/PKG-INFO
ros_rosidl_cmake-4.6.6.data/data/lib/python3.12/site-packages/rosidl_cmake-4.6.6-py3.12.egg-info/SOURCES.txt
ros_rosidl_cmake-4.6.6.data/data/lib/python3.12/site-packages/rosidl_cmake-4.6.6-py3.12.egg-info/dependency_links.txt
ros_rosidl_cmake-4.6.6.data/data/lib/python3.12/site-packages/rosidl_cmake-4.6.6-py3.12.egg-info/top_level.txt
ros_rosidl_cmake-4.6.6.data/data/share/ament_index/resource_index/package_run_dependencies/rosidl_cmake
ros_rosidl_cmake-4.6.6.data/data/share/ament_index/resource_index/packages/rosidl_cmake
ros_rosidl_cmake-4.6.6.data/data/share/ament_index/resource_index/parent_prefix_path/rosidl_cmake
ros_rosidl_cmake-4.6.6.data/data/share/rosidl_cmake/local_setup.bash
ros_rosidl_cmake-4.6.6.data/data/share/rosidl_cmake/local_setup.dsv
ros_rosidl_cmake-4.6.6.data/data/share/rosidl_cmake/local_setup.sh
ros_rosidl_cmake-4.6.6.data/data/share/rosidl_cmake/local_setup.zsh
ros_rosidl_cmake-4.6.6.data/data/share/rosidl_cmake/package.dsv
ros_rosidl_cmake-4.6.6.data/data/share/rosidl_cmake/package.xml
ros_rosidl_cmake-4.6.6.data/data/share/rosidl_cmake/cmake/rosidl_cmake-extras.cmake
ros_rosidl_cmake-4.6.6.data/data/share/rosidl_cmake/cmake/rosidl_cmake-extras.cmake.in
ros_rosidl_cmake-4.6.6.data/data/share/rosidl_cmake/cmake/rosidl_cmakeConfig-version.cmake
ros_rosidl_cmake-4.6.6.data/data/share/rosidl_cmake/cmake/rosidl_cmakeConfig.cmake
ros_rosidl_cmake-4.6.6.data/data/share/rosidl_cmake/cmake/rosidl_cmake_export_typesupport_libraries-extras.cmake.in
ros_rosidl_cmake-4.6.6.data/data/share/rosidl_cmake/cmake/rosidl_cmake_export_typesupport_libraries_package_hook.cmake
ros_rosidl_cmake-4.6.6.data/data/share/rosidl_cmake/cmake/rosidl_cmake_export_typesupport_targets-extras.cmake.in
ros_rosidl_cmake-4.6.6.data/data/share/rosidl_cmake/cmake/rosidl_cmake_export_typesupport_targets_package_hook.cmake
ros_rosidl_cmake-4.6.6.data/data/share/rosidl_cmake/cmake/rosidl_cmake_package_hook.cmake
ros_rosidl_cmake-4.6.6.data/data/share/rosidl_cmake/cmake/rosidl_export_typesupport_libraries.cmake
ros_rosidl_cmake-4.6.6.dist-info/METADATA
ros_rosidl_cmake-4.6.6.dist-info/WHEEL
ros_rosidl_cmake-4.6.6.dist-info/top_level.txt
ros_rosidl_cmake-4.6.6.dist-info/RECORD
