Metadata-Version: 2.4
Name: ros-rosidl-cmake
Version: 4.6.6
Summary: Wheel for the rosidl_cmake (ros-rosidl-cmake) ROS 2 package.
Requires-Dist: ros-rosidl-pycommon~=4.6.6
Dynamic: description
Dynamic: description-content-type
Dynamic: requires-dist
Dynamic: summary
